oedtools/__init__.py
oedtools/cli.py
oedtools/exceptions.py
oedtools/query.py
oedtools/report.py
oedtools/schema.py
oedtools/utils.py
oedtools/validate.py
oedtools/values.py
oedtools/schema/acc_def.csv
oedtools/schema/acc_schema.json
oedtools/schema/iso-3166-countrycodes.csv
oedtools/schema/iso-4217-currencies-old.csv
oedtools/schema/iso-4217-currencies.csv
oedtools/schema/loc_def.csv
oedtools/schema/loc_schema.json
oedtools/schema/master_def.csv
oedtools/schema/master_schema.json
oedtools/schema/reinsinfo_def.csv
oedtools/schema/reinsinfo_schema.json
oedtools/schema/reinsscope_def.csv
oedtools/schema/reinsscope_schema.json
oedtools/schema/schema_version.txt
oedtools/schema/spec.xlsx
oedtools/schema/values.csv
oedtools/schema/values.json
oedtools/schema/spec/AreaCode Values-Table 1.csv
oedtools/schema/spec/Changes-Table 1.csv
oedtools/schema/spec/Construction Values-Table 1.csv
oedtools/schema/spec/Country Values-Table 1.csv
oedtools/schema/spec/Currency Values-Table 1.csv
oedtools/schema/spec/Financial Code Values-Table 1.csv
oedtools/schema/spec/License-Table 1.csv
oedtools/schema/spec/Notes-Table 1.csv
oedtools/schema/spec/OED CR Field Appendix-Table 1.csv
oedtools/schema/spec/OED DB Data Types-Table 1.csv
oedtools/schema/spec/OED Input Fields-Table 1.csv
oedtools/schema/spec/Occupancy Values-Table 1.csv
oedtools/schema/spec/Other Values-Table 1.csv
oedtools/schema/spec/Peril Values-Table 1.csv
oedtools/schema/spec/README-Table 1.csv
oedtools/schema/spec.csv/AreaCode Values-Table 1.csv
oedtools/schema/spec.csv/Changes-Table 1.csv
oedtools/schema/spec.csv/Construction Values-Table 1.csv
oedtools/schema/spec.csv/Country Values-Table 1.csv
oedtools/schema/spec.csv/Currency Values-Table 1.csv
oedtools/schema/spec.csv/Financial Code Values-Table 1.csv
oedtools/schema/spec.csv/License-Table 1.csv
oedtools/schema/spec.csv/Notes-Table 1.csv
oedtools/schema/spec.csv/OED CR Field Appendix-Table 1.csv
oedtools/schema/spec.csv/OED DB Data Types-Table 1.csv
oedtools-1.0.2.dist-info/LICENSE
oedtools-1.0.2.dist-info/METADATA
oedtools-1.0.2.dist-info/WHEEL
oedtools-1.0.2.dist-info/top_level.txt
oedtools-1.0.2.dist-info/RECORD
