Metadata-Version: 2.1
Name: oedtools
Version: 1.0.2
Summary: Command-line OED file validation and query toolkit for the Simplitium OED (re)insurance exposure data format
Home-page: https://github.com/sr-murthy/oedtools
Author: Sandeep R Murthy
Author-email: smurthy@protonmail.ch
Maintainer: Sandeep R Murthy
Maintainer-email: smurthy@protonmail.ch
License: BSD 3-Clause
Keywords: Simplitium,Open Exposure Data (OED),exposure,insurance,reinsurance,catastrophe modelling
Platform: UNKNOWN
Classifier: Development Status :: 4 - Beta
Classifier: Environment :: Console
Classifier: Intended Audience :: Developers
Classifier: Intended Audience :: Education
Classifier: Intended Audience :: End Users/Desktop
Classifier: Intended Audience :: Financial and Insurance Industry
Classifier: Intended Audience :: Science/Research
Classifier: License :: Public Domain
Classifier: License :: OSI Approved :: BSD License
Classifier: Operating System :: OS Independent
Classifier: Programming Language :: Python
Classifier: Programming Language :: Python :: 3.6
Classifier: Topic :: Scientific/Engineering
Requires-Python: >=3.6
Requires-Dist: argparsetree (>=0.0.6)
Requires-Dist: future
Requires-Dist: numpy (>=1.14.0)
Requires-Dist: pandas (>=0.24.2)
